superduper_mongodb/__init__.py
superduper_mongodb/data_backend.py
superduper_mongodb/database_listener.py
superduper_mongodb/utils.py
superduper_mongodb/vector_search.py
superduper_mongodb-0.10.0.dist-info/licenses/LICENSE
superduper_mongodb-0.10.0.dist-info/METADATA
superduper_mongodb-0.10.0.dist-info/WHEEL
superduper_mongodb-0.10.0.dist-info/top_level.txt
superduper_mongodb-0.10.0.dist-info/RECORD
