Metadata-Version: 2.4
Name: superduper_mongodb
Version: 0.10.0
Summary: SuperDuper MongoDB is a Python library that provides a high-level API for working with MongoDB. It is built on top of pymongo and provides a more user-friendly interface for working with MongoDB.
Maintainer-email: "superduper.io, Inc." <opensource@superduper.io>
License: 
Project-URL: homepage, https://superduper.io
Project-URL: documentation, https://docs.superduper.io/docs/intro
Project-URL: source, https://github.com/superduper-io/superduper
Keywords: databases,mongodb,data-science,machine-learning,mlops,vector-database,ai
Requires-Python: >=3.10
License-File: LICENSE
Requires-Dist: mongomock
Requires-Dist: pymongo
Requires-Dist: click
Dynamic: license-file
